twitter/__init__.py
twitter/_capsolver/__init__.py
twitter/_capsolver/core/__init__.py
twitter/_capsolver/core/base.py
twitter/_capsolver/core/config.py
twitter/_capsolver/core/enum.py
twitter/_capsolver/core/serializer.py
twitter/_capsolver/fun_captcha.py
twitter/account.py
twitter/base/__init__.py
twitter/base/client.py
twitter/base/session.py
twitter/client.py
twitter/enums.py
twitter/errors.py
twitter/models.py
twitter/utils/__init__.py
twitter/utils/file.py
twitter/utils/html.py
twitter/utils/other.py
tweepy_self-1.11.1.dist-info/METADATA
tweepy_self-1.11.1.dist-info/WHEEL
tweepy_self-1.11.1.dist-info/RECORD
