Metadata-Version: 2.1
Name: tweepy-self
Version: 1.11.1
Summary: Twitter (selfbot) for Python!
Home-page: https://github.com/alenkimov/tweepy-self
Author: Alen
Author-email: alen.kimov@gmail.com
Requires-Python: >=3.11,<4.0
Classifier: Programming Language :: Python :: 3
Classifier: Programming Language :: Python :: 3.11
Classifier: Programming Language :: Python :: 3.12
Requires-Dist: aiohttp (>=3.9,<4.0)
Requires-Dist: beautifulsoup4 (>=4,<5)
Requires-Dist: better-proxy (>=1.1,<2.0)
Requires-Dist: curl_cffi (==0.6.2)
Requires-Dist: loguru (>=0.7,<0.8)
Requires-Dist: lxml (>=5,<6)
Requires-Dist: pydantic (>=2,<3)
Requires-Dist: pyotp (>=2,<3)
Requires-Dist: requests (>=2,<3)
Requires-Dist: tenacity (>=8,<9)
Requires-Dist: yarl (>=1,<2)
Project-URL: Repository, https://github.com/alenkimov/tweepy-self
Project-URL: Source, https://github.com/alenkimov/tweepy-self
